[
  {
    "workflow_id": "seed_txt2img_sdxl_base_v1",
    "name": "SDXL Text to Image Base",
    "task_type": "txt2img",
    "category": "image_generation",
    "inputs": [
      {
        "binding": {
          "node_id": "6",
          "class_type": "CLIPTextEncode",
          "input": "text",
          "default": "a cinematic photo of a futuristic city, ultra detailed, 8k"
        }
      },
      {
        "binding": {
          "node_id": "7",
          "class_type": "CLIPTextEncode",
          "input": "text",
          "default": "low quality, blurry, distorted, watermark, text"
        }
      },
      {
        "binding": {
          "node_id": "5",
          "class_type": "EmptyLatentImage",
          "input": "width",
          "default": 1024
        }
      },
      {
        "binding": {
          "node_id": "5",
          "class_type": "EmptyLatentImage",
          "input": "height",
          "default": 1024
        }
      },
      {
        "binding": {
          "node_id": "3",
          "class_type": "KSampler",
          "input": "steps",
          "default": 30
        }
      },
      {
        "binding": {
          "node_id": "3",
          "class_type": "KSampler",
          "input": "cfg",
          "default": 7.0
        }
      }
    ],
    "models": [
      "sd_xl_base_1.0.safetensors"
    ],
    "tags": [
      "sdxl",
      "txt2img",
      "base",
      "starter"
    ]
  },
  {
    "workflow_id": "seed_img2img_sdxl_denoise_v1",
    "name": "SDXL Image to Image Denoise",
    "task_type": "img2img",
    "category": "image_generation",
    "inputs": [
      {
        "binding": {
          "node_id": "10",
          "class_type": "LoadImage",
          "input": "image",
          "default": null
        }
      },
      {
        "binding": {
          "node_id": "6",
          "class_type": "CLIPTextEncode",
          "input": "text",
          "default": "enhance details, cinematic lighting, realistic texture"
        }
      },
      {
        "binding": {
          "node_id": "7",
          "class_type": "CLIPTextEncode",
          "input": "text",
          "default": "low quality, artifacts, blurry, oversharpened"
        }
      },
      {
        "binding": {
          "node_id": "3",
          "class_type": "KSampler",
          "input": "denoise",
          "default": 0.45
        }
      },
      {
        "binding": {
          "node_id": "3",
          "class_type": "KSampler",
          "input": "steps",
          "default": 25
        }
      }
    ],
    "models": [
      "sd_xl_base_1.0.safetensors"
    ],
    "tags": [
      "sdxl",
      "img2img",
      "denoise",
      "enhance"
    ]
  },
  {
    "workflow_id": "seed_inpaint_sdxl_mask_v1",
    "name": "SDXL Inpainting with Mask",
    "task_type": "inpaint",
    "category": "editing",
    "inputs": [
      {
        "binding": {
          "node_id": "10",
          "class_type": "LoadImage",
          "input": "image",
          "default": null
        }
      },
      {
        "binding": {
          "node_id": "11",
          "class_type": "LoadImageMask",
          "input": "image",
          "default": null
        }
      },
      {
        "binding": {
          "node_id": "6",
          "class_type": "CLIPTextEncode",
          "input": "text",
          "default": "seamless repair, match original lighting and texture"
        }
      },
      {
        "binding": {
          "node_id": "7",
          "class_type": "CLIPTextEncode",
          "input": "text",
          "default": "visible seam, mismatch, artifacts, low quality"
        }
      },
      {
        "binding": {
          "node_id": "3",
          "class_type": "KSampler",
          "input": "denoise",
          "default": 0.8
        }
      }
    ],
    "models": [
      "sd_xl_base_1.0.safetensors"
    ],
    "tags": [
      "sdxl",
      "inpaint",
      "mask",
      "edit"
    ]
  },
  {
    "workflow_id": "seed_sdxl_base_refiner_v1",
    "name": "SDXL Base + Refiner Two Stage",
    "task_type": "txt2img_refiner",
    "category": "image_generation",
    "inputs": [
      {
        "binding": {
          "node_id": "4",
          "class_type": "CheckpointLoaderSimple",
          "input": "ckpt_name",
          "default": "sd_xl_base_1.0.safetensors"
        }
      },
      {
        "binding": {
          "node_id": "12",
          "class_type": "CheckpointLoaderSimple",
          "input": "ckpt_name",
          "default": "sd_xl_refiner_1.0.safetensors"
        }
      },
      {
        "binding": {
          "node_id": "6",
          "class_type": "CLIPTextEncode",
          "input": "text",
          "default": "cinematic masterpiece, ultra detailed, dramatic lighting, high quality"
        }
      },
      {
        "binding": {
          "node_id": "7",
          "class_type": "CLIPTextEncode",
          "input": "text",
          "default": "low quality, blurry, jpeg artifacts, watermark, text"
        }
      },
      {
        "binding": {
          "node_id": "5",
          "class_type": "EmptyLatentImage",
          "input": "width",
          "default": 1024
        }
      },
      {
        "binding": {
          "node_id": "5",
          "class_type": "EmptyLatentImage",
          "input": "height",
          "default": 1024
        }
      },
      {
        "binding": {
          "node_id": "3",
          "class_type": "KSampler",
          "input": "steps",
          "default": 25
        }
      },
      {
        "binding": {
          "node_id": "13",
          "class_type": "KSampler",
          "input": "denoise",
          "default": 0.25
        }
      }
    ],
    "models": [
      "sd_xl_base_1.0.safetensors",
      "sd_xl_refiner_1.0.safetensors"
    ],
    "tags": [
      "sdxl",
      "refiner",
      "two-stage",
      "quality"
    ]
  },
  {
    "workflow_id": "seed_sd15_txt2img_basic_v1",
    "name": "Stable Diffusion 1.5 Text to Image",
    "task_type": "txt2img",
    "category": "image_generation",
    "inputs": [
      {
        "binding": {
          "node_id": "4",
          "class_type": "CheckpointLoaderSimple",
          "input": "ckpt_name",
          "default": "v1-5-pruned-emaonly.safetensors"
        }
      },
      {
        "binding": {
          "node_id": "6",
          "class_type": "CLIPTextEncode",
          "input": "text",
          "default": "best quality, highly detailed, cinematic lighting"
        }
      },
      {
        "binding": {
          "node_id": "7",
          "class_type": "CLIPTextEncode",
          "input": "text",
          "default": "worst quality, low quality, blurry, bad anatomy"
        }
      },
      {
        "binding": {
          "node_id": "5",
          "class_type": "EmptyLatentImage",
          "input": "width",
          "default": 512
        }
      },
      {
        "binding": {
          "node_id": "5",
          "class_type": "EmptyLatentImage",
          "input": "height",
          "default": 768
        }
      },
      {
        "binding": {
          "node_id": "3",
          "class_type": "KSampler",
          "input": "steps",
          "default": 28
        }
      },
      {
        "binding": {
          "node_id": "3",
          "class_type": "KSampler",
          "input": "cfg",
          "default": 7.5
        }
      }
    ],
    "models": [
      "v1-5-pruned-emaonly.safetensors"
    ],
    "tags": [
      "sd15",
      "txt2img",
      "basic",
      "starter"
    ]
  },
  {
    "workflow_id": "seed_sdxl_turbo_fast_txt2img_v1",
    "name": "SDXL Turbo Fast Text to Image",
    "task_type": "txt2img_fast",
    "category": "image_generation",
    "inputs": [
      {
        "binding": {
          "node_id": "4",
          "class_type": "CheckpointLoaderSimple",
          "input": "ckpt_name",
          "default": "sd_xl_turbo_1.0_fp16.safetensors"
        }
      },
      {
        "binding": {
          "node_id": "6",
          "class_type": "CLIPTextEncode",
          "input": "text",
          "default": "high quality cinematic image, detailed subject, clean composition"
        }
      },
      {
        "binding": {
          "node_id": "7",
          "class_type": "CLIPTextEncode",
          "input": "text",
          "default": "low quality, blurry, distorted"
        }
      },
      {
        "binding": {
          "node_id": "5",
          "class_type": "EmptyLatentImage",
          "input": "width",
          "default": 1024
        }
      },
      {
        "binding": {
          "node_id": "5",
          "class_type": "EmptyLatentImage",
          "input": "height",
          "default": 1024
        }
      },
      {
        "binding": {
          "node_id": "3",
          "class_type": "KSampler",
          "input": "steps",
          "default": 4
        }
      },
      {
        "binding": {
          "node_id": "3",
          "class_type": "KSampler",
          "input": "cfg",
          "default": 1.5
        }
      },
      {
        "binding": {
          "node_id": "3",
          "class_type": "KSampler",
          "input": "sampler_name",
          "default": "euler"
        }
      }
    ],
    "models": [
      "sd_xl_turbo_1.0_fp16.safetensors"
    ],
    "tags": [
      "sdxl",
      "turbo",
      "fast",
      "low-steps"
    ]
  },
  {
    "workflow_id": "seed_lcm_lora_sdxl_fast_v1",
    "name": "SDXL LCM LoRA Fast Generation",
    "task_type": "txt2img_lcm",
    "category": "image_generation",
    "inputs": [
      {
        "binding": {
          "node_id": "4",
          "class_type": "CheckpointLoaderSimple",
          "input": "ckpt_name",
          "default": "sd_xl_base_1.0.safetensors"
        }
      },
      {
        "binding": {
          "node_id": "50",
          "class_type": "LoraLoader",
          "input": "lora_name",
          "default": "lcm-lora-sdxl.safetensors"
        }
      },
      {
        "binding": {
          "node_id": "50",
          "class_type": "LoraLoader",
          "input": "strength_model",
          "default": 1.0
        }
      },
      {
        "binding": {
          "node_id": "50",
          "class_type": "LoraLoader",
          "input": "strength_clip",
          "default": 1.0
        }
      },
      {
        "binding": {
          "node_id": "6",
          "class_type": "CLIPTextEncode",
          "input": "text",
          "default": "high quality image, cinematic lighting, sharp details"
        }
      },
      {
        "binding": {
          "node_id": "3",
          "class_type": "KSampler",
          "input": "steps",
          "default": 8
        }
      },
      {
        "binding": {
          "node_id": "3",
          "class_type": "KSampler",
          "input": "cfg",
          "default": 2.0
        }
      },
      {
        "binding": {
          "node_id": "3",
          "class_type": "KSampler",
          "input": "sampler_name",
          "default": "lcm"
        }
      }
    ],
    "models": [
      "sd_xl_base_1.0.safetensors",
      "lcm-lora-sdxl.safetensors"
    ],
    "tags": [
      "sdxl",
      "lcm",
      "lora",
      "fast"
    ]
  }
]